CHANGES.md
MANIFEST.in
README.md
setup.py
pyramid_shopify_oauth/__init__.py
pyramid_shopify_oauth/views.py
pyramid_shopify_oauth.egg-info/PKG-INFO
pyramid_shopify_oauth.egg-info/SOURCES.txt
pyramid_shopify_oauth.egg-info/dependency_links.txt
pyramid_shopify_oauth.egg-info/requires.txt
pyramid_shopify_oauth.egg-info/top_level.txt