Metadata-Version: 1.1
Name: pyramid-shopify-oauth
Version: 0.0.1
Summary: create pyramid app without worrying about Shopify OAuth
Home-page: https://github.com/dakuang/pyramid_shopify_oauth
Author: Da Kuang
Author-email: dkuang1980@gmail.com
License: UNKNOWN
Keywords: pyramid python shopify oauth
Platform: UNKNOWN
Classifier: Topic :: Software Development :: Libraries :: Python Modules
Classifier: License :: OSI Approved :: MIT License
Classifier: Natural Language :: English
Classifier: Operating System :: OS Independent
Classifier: Programming Language :: Python
